linkgrid_agent/__init__.py
linkgrid_agent/agent.py
linkgrid_agent/config.py
linkgrid_agent-0.1.9.dist-info/METADATA
linkgrid_agent-0.1.9.dist-info/WHEEL
linkgrid_agent-0.1.9.dist-info/top_level.txt
linkgrid_agent-0.1.9.dist-info/RECORD
