Metadata-Version: 2.4
Name: linkgrid-agent
Version: 0.1.9
Summary: LinkGrid Agent - Python client for BitNet API
Home-page: https://github.com/OfficialDeepSaha/linkgrid-agent
Author: Deep Saha
Author-email: hiremeasadeveloper@gmail.com
Classifier: Programming Language :: Python :: 3
Classifier: License :: OSI Approved :: MIT License
Classifier: Operating System :: OS Independent
Requires-Python: >=3.9
Requires-Dist: httpx
Dynamic: author
Dynamic: author-email
Dynamic: classifier
Dynamic: description
Dynamic: description-content-type
Dynamic: home-page
Dynamic: requires-dist
Dynamic: requires-python
Dynamic: summary
